ragnar/__init__.py
ragnar/generators.py
ragnar/stream.py
ragnar-0.3.2.dist-info/AUTHORS.rst
ragnar-0.3.2.dist-info/LICENSE
ragnar-0.3.2.dist-info/METADATA
ragnar-0.3.2.dist-info/WHEEL
ragnar-0.3.2.dist-info/entry_points.txt
ragnar-0.3.2.dist-info/top_level.txt
ragnar-0.3.2.dist-info/RECORD
