Metadata-Version: 2.1
Name: ragnar
Version: 0.3.2
Summary: lightweight Extract-Transform-Load (ETL) framework for Python 3+
Home-page: https://github.com/juanmcristobal/ragnar
Author: juanmcristobal
Author-email: juanmcristobal@gmail.com
License: MIT license
Keywords: ragnar
Platform: UNKNOWN
Classifier: Development Status :: 4 - Beta
Classifier: Intended Audience :: Developers
Classifier: License :: OSI Approved :: MIT License
Classifier: Natural Language :: English
Classifier: Topic :: Documentation :: Sphinx
Classifier: Topic :: Text Processing
Classifier: Programming Language :: Python :: 3.5
Classifier: Programming Language :: Python :: 3.6
Classifier: Programming Language :: Python :: 3.7
Classifier: Programming Language :: Python :: 3.8
